<?xml version="1.0" encoding="utf-8" ?>
<dwsync>
<file name="african_cocktail.jpeg" server="sw01.bcc.cuny.edu" local="131260309620000000" remote="131260309610000000" Dst="1" />
<file name="african_cocktail.jpeg" server="sw01.bcc.cuny.edu/BIS12/" local="131260309620000000" remote="131575110280000000" Dst="1" />
<file name="banb2_green_jellow.png" server="sw01.bcc.cuny.edu/BIS12/" local="131249119860000000" remote="131575110280000000" Dst="1" />
<file name="logo.psd" server="sw01.bcc.cuny.edu/BIS12/" local="131573301420000000" remote="131575110280000000" Dst="1" />
<file name="logo.jpg" server="sw01.bcc.cuny.edu/BIS12/" local="131573268980000000" remote="131575110280000000" Dst="1" />
<file name="Likefacebook.png" server="sw01.bcc.cuny.edu/BIS12/" local="131563011120000000" remote="131575110280000000" Dst="1" />
<file name="logo_car_rental.jpg" server="sw01.bcc.cuny.edu/BIS12/" local="131573265420000000" remote="131575110290000000" Dst="1" />
<file name="2017-Toyota-Camry-Hybrid-TD-2.jpg" server="sw01.bcc.cuny.edu/BIS12/" local="131563039760000000" remote="131575110290000000" Dst="1" />
<file name="2017_chevrolet_malibu_sedan_premier_fq_oem_3_1280.jpeg" server="sw01.bcc.cuny.edu/BIS12/" local="131565389800000000" remote="131575110290000000" Dst="1" />
<file name="car-silhouette.jpg" server="sw01.bcc.cuny.edu/BIS12/" local="131573176000000000" remote="131575110290000000" Dst="1" />
<file name="logo_car.psd" server="sw01.bcc.cuny.edu/BIS12/" local="131573301880000000" remote="131575110290000000" Dst="1" />
<file name="whitecar .jpg" server="sw01.bcc.cuny.edu/BIS12/" local="131573240560000000" remote="131575110290000000" Dst="1" />
<file name="logo_blue.jpg" server="sw01.bcc.cuny.edu/BIS12/" local="131573299480000000" remote="131575110290000000" Dst="1" />
<file name="suv.jpeg" server="sw01.bcc.cuny.edu/BIS12/" local="131565413040000000" remote="131575110290000000" Dst="1" />
<file name="logo_car_rental.psd" server="sw01.bcc.cuny.edu/BIS12/" local="131573299800000000" remote="131575110290000000" Dst="1" />
<file name="logo_orange.jpg" server="sw01.bcc.cuny.edu/BIS12/" local="131574032460000000" remote="131575110290000000" Dst="1" />
<file name="logo_orange.psd" server="sw01.bcc.cuny.edu/BIS12/" local="131574048400000000" remote="131575110290000000" Dst="1" />
<file name="logo_orange2.jpg" server="sw01.bcc.cuny.edu/BIS12/" local="131574039840000000" remote="131575110290000000" Dst="1" />
<file name="logo_orange3.jpg" server="sw01.bcc.cuny.edu/BIS12/" local="131574042040000000" remote="131575110290000000" Dst="1" />
<file name="logo_orange4.jpg" server="sw01.bcc.cuny.edu/BIS12/" local="131574043200000000" remote="131575110290000000" Dst="1" />
<file name="logo_orange5.jpg" server="sw01.bcc.cuny.edu/BIS12/" local="131574049100000000" remote="131575110290000000" Dst="1" />
<file name="logo_orange6.jpg" server="sw01.bcc.cuny.edu/BIS12/" local="131574050500000000" remote="131575110290000000" Dst="1" />
<file name="logo_orangenew.jpg" server="sw01.bcc.cuny.edu/BIS12/" local="131574053940000000" remote="131575110300000000" Dst="1" />
<file name="logo_orangenew1.jpg" server="sw01.bcc.cuny.edu/BIS12/" local="131574056580000000" remote="131575110300000000" Dst="1" />
<file name="logo_orangenew3.jpg" server="sw01.bcc.cuny.edu/BIS12/" local="131574065780000000" remote="131575110300000000" Dst="1" />
<file name="logo_orangenew.psd" server="sw01.bcc.cuny.edu/BIS12/" local="131574066700000000" remote="131575110300000000" Dst="1" />
<file name="blackhybrid_cars_2017.jpg" server="sw01.bcc.cuny.edu/BIS12/" local="131574121020000000" remote="131575110470000000" Dst="1" />
<file name="red_hybrid_car.jpeg" server="sw01.bcc.cuny.edu/BIS12/" local="131574126100000000" remote="131575110480000000" Dst="1" />
<file name="black_luxery_car.jpeg" server="sw01.bcc.cuny.edu/BIS12/" local="131574136640000000" remote="131575110480000000" Dst="1" />
<file name="white_suv_car_Ford-Edge.jpeg" server="sw01.bcc.cuny.edu/BIS12/" local="131574144260000000" remote="131575110480000000" Dst="1" />
<file name="blue_regular_car_toyota-camry2018.jpeg" server="sw01.bcc.cuny.edu/BIS12/" local="131574163240000000" remote="131575110480000000" Dst="1" />
<file name="Luxery_Page_2018-Buick-Enclave-Avenir-front-side-view.jpg" server="sw01.bcc.cuny.edu/BIS12/" local="131574336980000000" remote="131575110480000000" Dst="1" />
<file name="regular_page_2017-Hyundai-Sonata-Sedan-Base-4dr-Sedan-Photo.png" server="sw01.bcc.cuny.edu/BIS12/" local="131574371300000000" remote="131575110480000000" Dst="1" />
<file name="hybrid_page_2018-toyota-camry-hybrid-review-2.jpg" server="sw01.bcc.cuny.edu/BIS12/" local="131574387120000000" remote="131575110480000000" Dst="1" />
<file name="black_luxery_car.jpeg " server="sw01.bcc.cuny.edu/BIS12/" local="131574136640000000" remote="131575110490000000" Dst="1" />
<file name="red_hybrid_car.jpeg " server="sw01.bcc.cuny.edu/BIS12/" local="131574126100000000" remote="131575110490000000" Dst="1" />
<file name="white_suv_car_Ford-Edge.jpeg " server="sw01.bcc.cuny.edu/BIS12/" local="131574144260000000" remote="131575110490000000" Dst="1" />
</dwsync>